MANIFEST.in
README
REQUIREMENTS
distribute_setup.py
setup.py
src/django_cherry.egg-info/PKG-INFO
src/django_cherry.egg-info/SOURCES.txt
src/django_cherry.egg-info/dependency_links.txt
src/django_cherry.egg-info/requires.txt
src/django_cherry.egg-info/top_level.txt
src/djcherry/__init__.py
src/djcherry/commands.py
src/djcherry/models.py
src/djcherry/wsgi.py