Metadata-Version: 1.0
Name: django-cherry
Version: 0.1.2
Summary: Run Django under the CherryPy WSGI server using django-boss.
Home-page: http://bitbucket.org/zacharyvoase/django-cherry
Author: Zachary Voase
Author-email: zacharyvoase@me.com
License: UNKNOWN
Platform: UNKNOWN
